know/__init__.py
know/_version.py
know/py.typed
know/classes/__init__.py
know/classes/activity.py
know/classes/airport.py
know/classes/appointment.py
know/classes/audio_frame.py
know/classes/birth.py
know/classes/birthday.py
know/classes/birthday_party.py
know/classes/buddhist_temple.py
know/classes/cafe.py
know/classes/church.py
know/classes/class_.py
know/classes/community.py
know/classes/company.py
know/classes/conference.py
know/classes/congregation.py
know/classes/consortium.py
know/classes/corporation.py
know/classes/death.py
know/classes/event.py
know/classes/family.py
know/classes/file.py
know/classes/government.py
know/classes/graduation.py
know/classes/group.py
know/classes/hindu_temple.py
know/classes/holiday.py
know/classes/hospital.py
know/classes/hotel.py
know/classes/image.py
know/classes/landmark.py
know/classes/link.py
know/classes/meeting.py
know/classes/meetup.py
know/classes/mosque.py
know/classes/nationality.py
know/classes/observation.py
know/classes/organization.py
know/classes/party.py
know/classes/percept.py
know/classes/person.py
know/classes/place.py
know/classes/pub.py
know/classes/restaurant.py
know/classes/school.py
know/classes/synagogue.py
know/classes/temple.py
know/classes/thing.py
know/classes/university.py
know/classes/venue.py
know/classes/wedding.py
know_py-0.0.21.dist-info/METADATA
know_py-0.0.21.dist-info/WHEEL
know_py-0.0.21.dist-info/licenses/UNLICENSE
know_py-0.0.21.dist-info/RECORD
