Metadata-Version: 2.4
Name: know.py
Version: 0.0.21
Summary: The KNOW Framework for Python
Project-URL: Homepage, https://know.dev
Project-URL: Repository, https://github.com/know-ontology/know.py
Project-URL: Changelog, https://github.com/know-ontology/know.py/blob/master/CHANGES.md
Project-URL: Releases, https://github.com/know-ontology/know.py/releases
Project-URL: Issues, https://github.com/know-ontology/know.py/issues
Project-URL: Documentation, https://github.com/know-ontology/know.py/blob/master/README.md
Author-email: KNOW Project <support@know.dev>
License-Expression: Unlicense
License-File: UNLICENSE
Classifier: Development Status :: 2 - Pre-Alpha
Classifier: Environment :: Console
Classifier: Intended Audience :: Developers
Classifier: Intended Audience :: Information Technology
Classifier: License :: Public Domain
Classifier: Natural Language :: English
Classifier: Operating System :: OS Independent
Classifier: Programming Language :: Python :: 3 :: Only
Classifier: Topic :: Software Development :: Libraries
Requires-Python: >=3.9
Requires-Dist: pillow
Requires-Dist: pydantic>=2
Provides-Extra: image
Requires-Dist: pillow; extra == 'image'
